gift_api.py
gift_api-1.0.dist-info/METADATA
gift_api-1.0.dist-info/WHEEL
gift_api-1.0.dist-info/entry_points.txt
gift_api-1.0.dist-info/top_level.txt
gift_api-1.0.dist-info/RECORD
