Metadata-Version: 2.4
Name: gift-api
Version: 1.0
Summary: One-file Python module for Telegram gifts with CLI
Author-email: Nsvl <you@example.com>
License: MIT
Requires-Python: >=3.8
Requires-Dist: requests>=2.28.0
Requires-Dist: telethon>=1.30.0
